tlc.v
/*
 * Moore FSM based traffic light controller
 */

module tlc #(
    parameter T_RED = 7'd100,
    parameter T_YELLOW = 4'd15,
    parameter T_GREEN = 6'd60,
    parameter T_PED_WALK = 5'd30
) (
    input wire clk,
    input wire rst_n,   // Asynchronous active low reset
    input wire ped_btn, // Button for pedestrians' signal

    output reg red,
    output reg yellow,
    output reg green,
    output reg ped_cross  // Pedestrian crossing light
);
  reg blink_pulse;
  reg [1:0] blink_ctr;

  // Independent counter for blinking yellow light (fallback)
  always @(posedge clk or negedge rst_n) begin
    if (!rst_n) begin
      blink_pulse <= 1'b0;
      blink_ctr   <= 2'b0;
    end else begin
      blink_ctr <= blink_ctr + 1;
      if (blink_ctr == 2'd3) blink_pulse <= ~blink_pulse;
    end
  end

  reg [1:0] state;
  reg [7:0] counter;
  reg       ped_req;  // Stores pending pedestrians' request
  reg       ped_btn_prev;  // Stores previous button value to prevent race conditions

  localparam S_RED = 2'b00;  // s0
  localparam S_YELLOW = 2'b01;  // s1
  localparam S_GREEN = 2'b10;  // s2
  localparam S_PED_WALK = 2'b11;  // s3

  always @(posedge clk or negedge rst_n) begin
    if (!rst_n) begin
      state <= S_RED;
      counter <= 8'b0;
      ped_req <= 1'b0;
      ped_btn_prev <= 1'b0;

      red <= 1'b1;  // Safe state as no vehicles or pedestrians move
      yellow <= 1'b0;
      green <= 1'b0;
      ped_cross <= 1'b0;

    end else begin
      counter <= counter + 1;
      if (ped_btn && !ped_btn_prev)
        ped_req <= 1'b1;  // Change only at rising edge (first instant) of button  
                          // press so requests don't get triggered multiple times
      ped_btn_prev <= ped_btn;
      case (state)

        S_RED: begin
          red <= 1'b1;
          yellow <= 1'b0;
          green <= 1'b0;
          ped_cross <= 1'b0;
          if (counter >= T_RED - 1) begin
            counter <= 8'b0;
            if (ped_req || (ped_btn && !ped_btn_prev)) begin
              ped_req <= 1'b0;
              state   <= S_PED_WALK;  // Move to pedestrian mode if pending requests
            end else state <= S_GREEN;  // else Go Green!
          end
        end

        S_YELLOW: begin
          red <= 1'b0;
          yellow <= 1'b1;
          green <= 1'b0;
          ped_cross <= 1'b0;
          if (counter >= T_YELLOW - 1) begin
            counter <= 8'b0;
            state   <= S_RED;
          end
        end

        S_GREEN: begin
          red <= 1'b0;
          yellow <= 1'b0;
          green <= 1'b1;
          ped_cross <= 1'b0;
          if (counter >= T_GREEN - 1) begin
            counter <= 8'b0;
            state   <= S_YELLOW;
          end
        end

        S_PED_WALK: begin
          red <= 1'b1;
          yellow <= 1'b0;
          green <= 1'b0;
          ped_cross <= 1'b1;
          if (counter >= T_PED_WALK - 1) begin
            counter <= 8'b0;
            state   <= S_GREEN;
          end
        end

        default: begin
          red <= 1'b0;
          yellow <= blink_pulse;  // Distinguishing behaviour to signal that 
                                  // there's a fault with the machine's states
          green <= 1'b0;
          ped_cross <= 1'b0;
          state <= S_RED;  // Move to safe state immediately after
          counter <= 8'b0;
        end

      endcase
    end
  end

endmodule

TLC.srcs/sources_1/imports/TLC/test_tlc.v
`timescale 1ns / 1ps


module tb_tlc;
  reg clk = 0, rst_n = 0, ped_btn = 0;
  wire red, yellow, green, ped_cross;

  tlc #(
      .T_RED(10),
      .T_YELLOW(2),
      .T_GREEN(6),
      .T_PED_WALK(4)
  ) uut (
      .clk(clk),
      .rst_n(rst_n),
      .ped_btn(ped_btn),
      .red(red),
      .yellow(yellow),
      .green(green),
      .ped_cross(ped_cross)
  );

  initial forever #5 clk = ~clk;

  task check_outputs;
    input expc_red, expc_yellow, expc_green, expc_ped;
    input [80*8:1] test_name;

    begin
      if (red!==expc_red||yellow!==expc_yellow||green!==expc_green||ped_cross!==expc_ped) begin
        $display("[ERROR] %s failed at time %0t!", test_name, $time);
        $display("        Expected: R=%b Y=%b G=%b P=%b", expc_red, expc_yellow, expc_green,
                 expc_ped);
        $display("        Got     : R=%b Y=%b G=%b P=%b", red, yellow, green, ped_cross);
      end else begin
        $display("[PASS] %s at time %0t", test_name, $time);
      end
    end
  endtask

  initial begin
    $dumpfile("dump_tlc.vcd");
    $dumpvars(0, tb_tlc);

    // Verify initialization reset
    #15 rst_n = 1;
    check_outputs(1, 0, 0, 0, "Initial Reset to RED");

    #80 begin
      @(posedge clk) ped_btn <= 1;
      @(posedge clk) ped_btn <= 0;
    end

    // Handle simultaneous button edge
    @(posedge clk) #1 check_outputs(1, 0, 0, 1, "Simultaneous edge routes to PED_WALK");

    // Post-walk transition to green
    #40 check_outputs(0, 0, 1, 0, "Transitions from PED_WALK to GREEN");

    // Check spamming button behavior
    repeat (4) @(posedge clk) ped_btn <= ~ped_btn;
    #100 check_outputs(1, 0, 0, 0, "Transitions to RED despite spamming");

    // Verify pre-reset green state
    #120 check_outputs(0, 0, 1, 0, "Before Async Reset (State = GREEN)");
    rst_n = 0;

    // Asynchronous reset safety check
    #1 check_outputs(1, 0, 0, 0, "Immediate Async Reset Snap to RED");
    rst_n = 1;

    // Verify undefined state recovery
    #20 uut.state = 2'bxx;
    #10 @(posedge clk) #1 check_outputs(1, 0, 0, 0, "Fault State recovery to RED");

    #44 $display("All tests completed");
    $finish;
  end

endmodule

TLC.sim/sim_1/behav/xsim/dump_tlc.vcd
$date
   Fri Jun 19 23:36:37 2026
$end

$version
  2025.2
  $dumpfile ("dump_tlc.vcd") 
$end

$timescale
  1ps
$end

$scope module tb_tlc $end
$var reg 1 ! clk $end
$var reg 1 " rst_n $end
$var reg 1 # ped_btn $end
$var wire 1 $ red $end
$var wire 1 % yellow $end
$var wire 1 & green $end
$var wire 1 ' ped_cross $end
$scope module uut $end
$var wire 1 ( clk $end
$var wire 1 ) rst_n $end
$var wire 1 * ped_btn $end
$var reg 1 + red $end
$var reg 1 , yellow $end
$var reg 1 - green $end
$var reg 1 . ped_cross $end
$var reg 1 / blink_pulse $end
$var reg 2 0 blink_ctr [1:0] $end
$var reg 2 1 state [1:0] $end
$var reg 8 2 counter [7:0] $end
$var reg 1 3 ped_req $end
$var reg 1 4 ped_btn_prev $end
$upscope $end
$scope task check_outputs $end
$var reg 1 5 expc_red $end
$var reg 1 6 expc_yellow $end
$var reg 1 7 expc_green $end
$var reg 1 8 expc_ped $end
$var reg 640 9 test_name [639:0] $end
$upscope $end
$upscope $end
$enddefinitions $end

#0
$dumpvars
0!
0"
0#
1$
0%
0&
0'
0(
0)
0*
1+
0,
0-
0.
0/
b0 0
b0 1
b0 2
03
04
x5
x6
x7
x8
bx 9
$end

#5000
1!
1(

#10000
0!
0(

#15000
1!
1"
1(
1)
b1 0
b1 2
15
06
07
08
b100100101101110011010010111010001101001011000010110110000100000010100100110010101110011011001010111010000100000011101000110111100100000010100100100010101000100 9

#20000
0!
0(

#25000
1!
1(
b10 0
b10 2

#30000
0!
0(

#35000
1!
1(
b11 0
b11 2

#40000
0!
0(

#45000
1!
1(
1/
b0 0
b100 2

#50000
0!
0(

#55000
1!
1(
b1 0
b101 2

#60000
0!
0(

#65000
1!
1(
b10 0
b110 2

#70000
0!
0(

#75000
1!
1(
b11 0
b111 2

#80000
0!
0(

#85000
1!
1(
0/
b0 0
b1000 2

#90000
0!
0(

#95000
1!
1#
1(
1*
b1 0
b1001 2

#100000
0!
0(

#105000
1!
0#
1(
0*
b10 0
b11 1
b0 2
03
14

#110000
0!
0(

#115000
1!
1'
1(
1.
b11 0
b1 2
04

#116000
18
b10100110110100101101101011101010110110001110100011000010110111001100101011011110111010101110011001000000110010101100100011001110110010100100000011100100110111101110101011101000110010101110011001000000111010001101111001000000101000001000101010001000101111101010111010000010100110001001011 9

#120000
0!
0(

#125000
1!
1(
1/
b0 0
b10 2

#130000
0!
0(

#135000
1!
1(
b1 0
b11 2

#140000
0!
0(

#145000
1!
1(
b10 0
b10 1
b0 2

#150000
0!
0(

#155000
1!
0$
1&
0'
1(
0+
1-
0.
b11 0
b1 2

#156000
05
17
08
b1010100011100100110000101101110011100110110100101110100011010010110111101101110011100110010000001100110011100100110111101101101001000000101000001000101010001000101111101010111010000010100110001001011001000000111010001101111001000000100011101010010010001010100010101001110 9

#160000
0!
0(

#165000
1!
1#
1(
1*
0/
b0 0
b10 2

#170000
0!
0(

#175000
1!
0#
1(
0*
b1 0
b11 2
13
14

#180000
0!
0(

#185000
1!
1#
1(
1*
b10 0
b100 2
04

#190000
0!
0(

#195000
1!
0#
1(
0*
b11 0
b101 2
14

#200000
0!
0(

#205000
1!
1(
1/
b0 0
b1 1
b0 2
04

#210000
0!
0(

#215000
1!
1%
0&
1(
1,
0-
b1 0
b1 2

#220000
0!
0(

#225000
1!
1(
b10 0
b0 1
b0 2

#230000
0!
0(

#235000
1!
1$
0%
1(
1+
0,
b11 0
b1 2

#240000
0!
0(

#245000
1!
1(
0/
b0 0
b10 2

#250000
0!
0(

#255000
1!
1(
b1 0
b11 2

#260000
0!
0(

#265000
1!
1(
b10 0
b100 2

#270000
0!
0(

#275000
1!
1(
b11 0
b101 2

#280000
0!
0(

#285000
1!
1(
1/
b0 0
b110 2

#290000
0!
0(

#295000
1!
1(
b1 0
b111 2
15
07
b101010001110010011000010110111001110011011010010111010001101001011011110110111001110011001000000111010001101111001000000101001001000101010001000010000001100100011001010111001101110000011010010111010001100101001000000111001101110000011000010110110101101101011010010110111001100111 9

#300000
0!
0(

#305000
1!
1(
b10 0
b1000 2

#310000
0!
0(

#315000
1!
1(
b11 0
b1001 2

#320000
0!
0(

#325000
1!
1(
0/
b0 0
b11 1
b0 2
03

#330000
0!
0(

#335000
1!
1'
1(
1.
b1 0
b1 2

#340000
0!
0(

#345000
1!
1(
b10 0
b10 2

#350000
0!
0(

#355000
1!
1(
b11 0
b11 2

#360000
0!
0(

#365000
1!
1(
1/
b0 0
b10 1
b0 2

#370000
0!
0(

#375000
1!
0$
1&
0'
1(
0+
1-
0.
b1 0
b1 2

#380000
0!
0(

#385000
1!
1(
b10 0
b10 2

#390000
0!
0(

#395000
1!
1(
b11 0
b11 2

#400000
0!
0(

#405000
1!
1(
0/
b0 0
b100 2

#410000
0!
0(

#415000
1!
0"
1$
0&
1(
0)
1+
0-
b0 1
b0 2
05
17
b1000010011001010110011001101111011100100110010100100000010000010111001101111001011011100110001100100000010100100110010101110011011001010111010000100000001010000101001101110100011000010111010001100101001000000011110100100000010001110101001001000101010001010100111000101001 9

#416000
1"
1)
15
07
b10010010110110101101101011001010110010001101001011000010111010001100101001000000100000101110011011110010110111001100011001000000101001001100101011100110110010101110100001000000101001101101110011000010111000000100000011101000110111100100000010100100100010101000100 9

#420000
0!
0(

#425000
1!
1(
b1 0
b1 2

#430000
0!
0(

#435000
1!
1(
b10 0
b10 2

#436000
bx 1

#440000
0!
0(

#445000
1!
0$
1(
0+
b11 0
b0 1
b0 2

#450000
0!
0(

#455000
1!
1$
1(
1+
1/
b0 0
b1 2

#456000
b10001100110000101110101011011000111010000100000010100110111010001100001011101000110010100100000011100100110010101100011011011110111011001100101011100100111100100100000011101000110111100100000010100100100010101000100 9

#460000
0!
0(

#465000
1!
1(
b1 0
b10 2

#470000
0!
0(

#475000
1!
1(
b10 0
b11 2

#480000
0!
0(

#485000
1!
1(
b11 0
b100 2

#490000
0!
0(

#495000
1!
1(
0/
b0 0
b101 2
